Documint-16.4.0.dist-info/DESCRIPTION.rst
Documint-16.4.0.dist-info/METADATA
Documint-16.4.0.dist-info/RECORD
Documint-16.4.0.dist-info/WHEEL
Documint-16.4.0.dist-info/metadata.json
Documint-16.4.0.dist-info/top_level.txt
documint/__init__.py
documint/_version.py
documint/client.py
documint/commands.py
documint/errors.py
documint/mediumbox.py
documint/util.py
documint/extproc/__init__.py
documint/extproc/common.py
documint/extproc/css2xslfo.py
documint/extproc/fop.py
documint/extproc/neon.py
documint/test/__init__.py
documint/test/test_commands.py
documint/test/test_css2xslfo.py
documint/test/test_neon.py
documint/test/test_util.py
documint/test/data/broken.html
documint/test/data/keystore.jks
documint/test/data/test.pdf
twisted/plugins/documint_service.py
