Metadata-Version: 2.0
Name: Documint
Version: 16.4.0
Summary: UNKNOWN
Home-page: https://github.com/fusionapp/documint
Author: UNKNOWN
Author-email: UNKNOWN
License: UNKNOWN
Platform: UNKNOWN
Classifier: Development Status :: 3 - Alpha
Classifier: Framework :: Twisted
Classifier: Intended Audience :: Developers
Classifier: Operating System :: OS Independent
Classifier: Programming Language :: Python :: 2.7
Classifier: Topic :: Text Processing :: Markup :: HTML
Requires-Dist: Twisted[tls]
Requires-Dist: lxml (>=3.6.0)
